odoo/addons/report_qweb_pdf_watermark/README.rst
odoo/addons/report_qweb_pdf_watermark/__init__.py
odoo/addons/report_qweb_pdf_watermark/__manifest__.py
odoo/addons/report_qweb_pdf_watermark/demo/report.xml
odoo/addons/report_qweb_pdf_watermark/i18n/ca.po
odoo/addons/report_qweb_pdf_watermark/i18n/da.po
odoo/addons/report_qweb_pdf_watermark/i18n/de.po
odoo/addons/report_qweb_pdf_watermark/i18n/el_GR.po
odoo/addons/report_qweb_pdf_watermark/i18n/es.po
odoo/addons/report_qweb_pdf_watermark/i18n/es_CO.po
odoo/addons/report_qweb_pdf_watermark/i18n/fr.po
odoo/addons/report_qweb_pdf_watermark/i18n/gl.po
odoo/addons/report_qweb_pdf_watermark/i18n/hr.po
odoo/addons/report_qweb_pdf_watermark/i18n/hr_HR.po
odoo/addons/report_qweb_pdf_watermark/i18n/it.po
odoo/addons/report_qweb_pdf_watermark/i18n/nb_NO.po
odoo/addons/report_qweb_pdf_watermark/i18n/nl_NL.po
odoo/addons/report_qweb_pdf_watermark/i18n/pl.po
odoo/addons/report_qweb_pdf_watermark/i18n/pt.po
odoo/addons/report_qweb_pdf_watermark/i18n/pt_BR.po
odoo/addons/report_qweb_pdf_watermark/i18n/pt_PT.po
odoo/addons/report_qweb_pdf_watermark/i18n/report_qweb_pdf_watermark.pot
odoo/addons/report_qweb_pdf_watermark/i18n/sl.po
odoo/addons/report_qweb_pdf_watermark/i18n/tr.po
odoo/addons/report_qweb_pdf_watermark/i18n/tr_TR.po
odoo/addons/report_qweb_pdf_watermark/models/__init__.py
odoo/addons/report_qweb_pdf_watermark/models/report.py
odoo/addons/report_qweb_pdf_watermark/static/description/icon.png
odoo/addons/report_qweb_pdf_watermark/static/src/css/report_qweb_pdf_watermark.css
odoo/addons/report_qweb_pdf_watermark/tests/__init__.py
odoo/addons/report_qweb_pdf_watermark/tests/test_report_qweb_pdf_watermark.py
odoo/addons/report_qweb_pdf_watermark/views/ir_actions_report_xml.xml
odoo/addons/report_qweb_pdf_watermark/views/layout_templates.xml
odoo11_addon_report_qweb_pdf_watermark-11.0.1.0.0.99.dev2.dist-info/METADATA
odoo11_addon_report_qweb_pdf_watermark-11.0.1.0.0.99.dev2.dist-info/RECORD
odoo11_addon_report_qweb_pdf_watermark-11.0.1.0.0.99.dev2.dist-info/WHEEL
odoo11_addon_report_qweb_pdf_watermark-11.0.1.0.0.99.dev2.dist-info/top_level.txt
